antsys/__init__.py
antsys/antsys.py
antsys-0.1.44.dist-info/LICENSE
antsys-0.1.44.dist-info/METADATA
antsys-0.1.44.dist-info/WHEEL
antsys-0.1.44.dist-info/top_level.txt
antsys-0.1.44.dist-info/RECORD
